examples/__init__.py
examples/basic.py
examples/batch.py
examples/convenience.py
examples/websocket.py
xrpc/__init__.py
xrpc/client.py
xrpc/methods.py
xrpc/types.py
xrpc/websocket.py
xrpc_pro_sdk-1.1.0.dist-info/licenses/LICENSE
xrpc_pro_sdk-1.1.0.dist-info/METADATA
xrpc_pro_sdk-1.1.0.dist-info/WHEEL
xrpc_pro_sdk-1.1.0.dist-info/top_level.txt
xrpc_pro_sdk-1.1.0.dist-info/RECORD
