Metadata-Version: 2.4
Name: xrpc-pro-sdk
Version: 1.1.0
Summary: Official Python SDK for xRPC - Multi-chain RPC Gateway
Home-page: https://app.xrpc.pro
Author: xRPC
Author-email: xRPC <support@xrpc.pro>
License-Expression: MIT
Project-URL: Homepage, https://app.xrpc.pro
Project-URL: Documentation, https://docs.xrpc.pro
Project-URL: Support, https://t.me/xnode_support
Project-URL: Repository, https://github.com/xrpcpro/xrpc-sdk-python
Keywords: rpc,ethereum,blockchain,web3,json-rpc,multi-chain,polygon,arbitrum,optimism,base,beacon,wss,websocket,python,sdk,api
Classifier: Development Status :: 4 - Beta
Classifier: Intended Audience :: Developers
Classifier: Programming Language :: Python :: 3
Classifier: Programming Language :: Python :: 3.8
Classifier: Programming Language :: Python :: 3.9
Classifier: Programming Language :: Python :: 3.10
Classifier: Programming Language :: Python :: 3.11
Classifier: Programming Language :: Python :: 3.12
Classifier: Topic :: Software Development :: Libraries :: Python Modules
Classifier: Topic :: Internet
Requires-Python: >=3.8
License-File: LICENSE
Requires-Dist: requests>=2.31.0
Requires-Dist: urllib3>=2.0.0
Provides-Extra: websocket
Requires-Dist: websockets>=12.0; extra == "websocket"
Provides-Extra: dev
Requires-Dist: pytest>=7.4.0; extra == "dev"
Requires-Dist: pytest-cov>=4.1.0; extra == "dev"
Requires-Dist: black>=23.0.0; extra == "dev"
Requires-Dist: mypy>=1.5.0; extra == "dev"
Requires-Dist: ruff>=0.1.0; extra == "dev"
Dynamic: author
Dynamic: home-page
Dynamic: license-file
Dynamic: requires-python
